andres_server/__init__.py
andres_server/server.py
andres_server-0.1.1.dist-info/METADATA
andres_server-0.1.1.dist-info/WHEEL
andres_server-0.1.1.dist-info/entry_points.txt
andres_server-0.1.1.dist-info/RECORD
