Metadata-Version: 2.3
Name: andres-server
Version: 0.1.1
Summary: Andre's Rainbow Land with cute kittens and AI
Author-email: Andre Ratzenberger <andre.ratzenberger@whiteduck.de>
Requires-Python: >=3.10
Requires-Dist: mcp>=1.0.0
Requires-Dist: starlette>=0.41.3
